<circuits>
    <circuit>
        <id>2ca3297c-bd3a-11e6-a4a6-cec0c932ce01</id>
        <name>Australia</name>
        <date>26-3-2016</date>
        <weather>50</weather>
    </circuit>
    <circuit>
        <id>2ca32bc0-bd3a-11e6-a4a6-cec0c932ce01</id>
        <name>China</name>
        <date>9-4-2016</date>
        <weather>14</weather>
    </circuit>
    <circuit>
        <id>2ca32cba-bd3a-11e6-a4a6-cec0c932ce01</id>
        <name>Bahrain</name>
        <date>16-4-2016</date>
        <weather>3</weather>
    </circuit>
    <circuit>
        <id>2ca32d96-bd3a-11e6-a4a6-cec0c932ce01</id>
        <name>Russia</name>
        <date>30-4-2016</date>
        <weather>33</weather>
    </circuit>
    <circuit>
        <id>2ca32e72-bd3a-11e6-a4a6-cec0c932ce01</id>
        <name>Spain</name>
        <date>14-5-2016</date>
        <weather>10</weather>
    </circuit>
    <circuit>
        <id>2ca32f44-bd3a-11e6-a4a6-cec0c932ce01</id>
        <name>Monaco</name>
        <date>28-5-2016</date>
        <weather>14</weather>
    </circuit>
    <circuit>
        <id>2ca330ca-bd3a-11e6-a4a6-cec0c932ce01</id>
        <name>Canada</name>
        <date>11-6-2016</date>
        <weather>23</weather>
    </circuit>
    <circuit>
        <id>2ca334d0-bd3a-11e6-a4a6-cec0c932ce01</id>
        <name>Europe</name>
        <date>18-6-2016</date>
        <weather>40</weather>
    </circuit>
    <circuit>
        <id>2ca335ac-bd3a-11e6-a4a6-cec0c932ce01</id>
        <name>Austria</name>
        <date>2-7-2016</date>
        <weather>47</weather>
    </circuit>
    <circuit>
        <id>2ca33688-bd3a-11e6-a4a6-cec0c932ce01</id>
        <name>United Kingdom</name>
        <date>9-7-2016</date>
        <weather>65</weather>
    </circuit>
    <circuit>
        <id>2ca33750-bd3a-11e6-a4a6-cec0c932ce01</id>
        <name>Hungary</name>
        <date>23-7-2016</date>
        <weather>29</weather>
    </circuit>
    <circuit>
        <id>2ca33818-bd3a-11e6-a4a6-cec0c932ce01</id>
        <name>Germany</name>
        <date>30-7-2016</date>
        <weather>38</weather>
    </circuit>
    <circuit>
        <id>2ca338e0-bd3a-11e6-a4a6-cec0c932ce01</id>
        <name>Belgium</name>
        <date>27-8-2016</date>
        <weather>43</weather>
    </circuit>
    <circuit>
        <id>58914f36-bd5e-11e6-a4a6-cec0c932ce01</id>
        <name>Italy</name>
        <date>3-9-2016</date>
        <weather>34</weather>
    </circuit>
    <circuit>
        <id>589151c0-bd5e-11e6-a4a6-cec0c932ce01</id>
        <name>Malaysia</name>
        <date>17-9-2016</date>
        <weather>78</weather>
    </circuit>
    <circuit>
        <id>5891530a-bd5e-11e6-a4a6-cec0c932ce01</id>
        <name>Singapore</name>
        <date>1-10-2016</date>
        <weather>46</weather>
    </circuit>
    <circuit>
        <id>589153e6-bd5e-11e6-a4a6-cec0c932ce01</id>
        <name>Japan</name>
        <date>8-10-2016</date>
        <weather>47</weather>
    </circuit>
    <circuit>
        <id>589154b8-bd5e-11e6-a4a6-cec0c932ce01</id>
        <name>United States</name>
        <date>22-10-2016</date>
        <weather>23</weather>
    </circuit>
    <circuit>
        <id>58915580-bd5e-11e6-a4a6-cec0c932ce01</id>
        <name>Mexico</name>
        <date>5-11-2016</date>
        <weather>18</weather>
    </circuit>
    <circuit>
        <id>58915954-bd5e-11e6-a4a6-cec0c932ce01</id>
        <name>Brazil</name>
        <date>12-11-2016</date>
        <weather>16</weather>
    </circuit>
    <circuit>
        <id>58915a30-bd5e-11e6-a4a6-cec0c932ce01</id>
        <name>Abu Dhabi</name>
        <date>26-11-2016</date>
        <weather>0</weather>
    </circuit>
</circuits>
